eurodem2km/__init__.py
eurodem2km/__main__.py
eurodem2km/api.py
eurodem2km/dems/DEM_Europe_2km.zip
eurodem2km/dems/__init__.py
eurodem2km-1.0.5.dist-info/LICENSE
eurodem2km-1.0.5.dist-info/METADATA
eurodem2km-1.0.5.dist-info/WHEEL
eurodem2km-1.0.5.dist-info/entry_points.txt
eurodem2km-1.0.5.dist-info/top_level.txt
eurodem2km-1.0.5.dist-info/RECORD
