Metadata-Version: 2.1
Name: eurodem2km
Version: 1.0.5
Summary: Provides local API to get Altitude of any point in Europe by Lat/Lon coordinates.
Author-email: Marco Foi <foimarco@gmail.com>
Keywords: dem,altitude,2km
Classifier: License :: OSI Approved :: MIT License
Classifier: Programming Language :: Python
Classifier: Programming Language :: Python :: 3
Requires-Python: >=3.8
License-File: LICENSE
Requires-Dist: rasterio (>=1.3.5)
